README
setup.py
live_stylus/__init__.py
live_stylus.egg-info/PKG-INFO
live_stylus.egg-info/SOURCES.txt
live_stylus.egg-info/dependency_links.txt
live_stylus.egg-info/requires.txt
live_stylus.egg-info/top_level.txt