Metadata-Version: 1.0
Name: live-stylus
Version: 0.2.3
Summary: Convert stylus to css real time. Easily used by any web framwork.
Home-page: https://github.com/allenm/live-py-stylus
Author: Allen.M
Author-email: menghonglun@gmail.com
License: MIT
Keywords: stylus css
Platform: UNKNOWN
Classifier: Development Status :: 4 - Beta
Classifier: Topic :: Utilities
Classifier: License :: OSI Approved :: BSD License
